[{
    "title": "只有宽高",
    "fragment": "<div></div>",
    "stylesheet": "div { width: 100px; height: 100px; background-color: #fff;}",
    "anwser": {
      "attr": {},
      "rect": {
        "x": 0,
        "y": 0,
        "left": 0,
        "top": 0,
        "width": 1519,
        "height": 100
      },
      "tagName": "BODY",
      "nodeType": 1,
      "style": {},
      "id": "",
      "className": "",
      "uuid": "uuid_0",
      "children": [{
        "attr": {},
        "rect": {
          "x": 0,
          "y": 0,
          "left": 0,
          "top": 0,
          "width": 100,
          "height": 100
        },
        "tagName": "DIV",
        "nodeType": 1,
        "style": {
          "width": "100px",
          "height": "100px",
          "background-color": "rgb(255, 255, 255)"
        },
        "id": "",
        "className": "",
        "uuid": "uuid_0_0",
        "children": []
      }]
    }
  },
  {
    "title": "带上 padding/margin",
    "fragment": "<div></div>",
    "stylesheet": "div { width: 100px; height: 100px; background-color: #fff; padding: 20px; margin: 30px;}",
    "anwser": {
      "attr": {},
      "rect": {
        "x": 0,
        "y": 30,
        "left": 0,
        "top": 30,
        "width": 1519,
        "height": 140
      },
      "tagName": "BODY",
      "nodeType": 1,
      "style": {},
      "id": "",
      "className": "",
      "uuid": "uuid_0",
      "children": [{
        "attr": {},
        "rect": {
          "x": 30,
          "y": 30,
          "left": 0,
          "top": 30,
          "width": 140,
          "height": 140
        },
        "tagName": "DIV",
        "nodeType": 1,
        "style": {
          "width": "100px",
          "height": "100px",
          "background-color": "rgb(255, 255, 255)",
          "padding": "20px",
          "margin": "30px"
        },
        "id": "",
        "className": "",
        "uuid": "uuid_0_0",
        "children": []
      }]
    }
  }
]